imshowtk/__init__.py
imshowtk/_version.py
imshowtk/imshowtk.py
imshowTk-1.0.0.dist-info/LICENSE
imshowTk-1.0.0.dist-info/METADATA
imshowTk-1.0.0.dist-info/WHEEL
imshowTk-1.0.0.dist-info/top_level.txt
imshowTk-1.0.0.dist-info/RECORD
