Metadata-Version: 2.1
Name: imshowTk
Version: 1.0.0
Summary: A lightweight replacement for openCV imshow using Tk
Home-page: https://github.com/SciKit-Surgery/imshowTk
Author: Stephen Thompson
Author-email: s.thompson@ucl.ac.uk
License: BSD-3 license
Keywords: medical imaging
Platform: UNKNOWN
Classifier: Development Status :: 3 - Alpha
Classifier: Intended Audience :: Developers
Classifier: Intended Audience :: Healthcare Industry
Classifier: Intended Audience :: Information Technology
Classifier: Intended Audience :: Science/Research
Classifier: License :: OSI Approved :: BSD License
Classifier: Programming Language :: Python
Classifier: Programming Language :: Python :: 2
Classifier: Programming Language :: Python :: 3
Classifier: Topic :: Scientific/Engineering :: Information Analysis
Classifier: Topic :: Scientific/Engineering :: Medical Science Apps.
